{
  "name": "Онбординг нового поставщика",
  "steps": [
    {
      "name": "Ввод данных",
      "entity": "customer",
      "template": "form",
      "stepIndex": 1,
      "description": "Основные реквизиты компании",
      "transitions": null,
      "entityFields": [
        "name",
        "inn",
        "kpp"
      ]
    },
    {
      "name": "Контактное лицо",
      "entity": "customerContact",
      "template": "form",
      "stepIndex": 2,
      "description": "Данные ответственного сотрудника",
      "transitions": null,
      "entityFields": [
        "fullName",
        "email",
        "phone"
      ]
    },
    {
      "name": "Финальная проверка",
      "entity": "customer",
      "template": "form",
      "stepIndex": 3,
      "description": "Подтверждение данных перед сохранением",
      "transitions": null,
      "entityFields": [
        "directorName",
        "legalAddress"
      ]
    }
  ],
  "description": "Процесс регистрации и верификации нового поставщика в системе"
}